{
  "generatedAt": "2026-07-21T06:42:58.368Z",
  "source": "snapshot",
  "errors": {
    "binance": "451  from https://fapi.binance.com/fapi/v1/premiumIndex",
    "bybit": "403 Forbidden from https://api.bytick.com/v5/market/tickers?category=linear"
  },
  "hyperliquid": {
    "predictedFundings": [
      [
        "AVAX",
        [
          [
            "BinPerp",
            {
              "fundingRate": "0.0000802",
              "nextFundingTime": 1784620800000,
              "fundingIntervalHours": 8
            }
          ],
          [
            "HlPerp",
            {
              "fundingRate": "0.0000125",
              "nextFundingTime": 1784613600000,
              "fundingIntervalHours": 1
            }
          ],
          [
            "BybitPerp",
            {
              "fundingRate": "0.00004851",
              "nextFundingTime": 1784620800000,
              "fundingIntervalHours": 8
            }
          ]
        ]
      ],
      [
        "BNB",
        [
          [
            "BinPerp",
            {
              "fundingRate": "0.00008676",
              "nextFundingTime": 1784620800000,
              "fundingIntervalHours": 8
            }
          ],
          [
            "HlPerp",
            {
              "fundingRate": "0.0000125",
              "nextFundingTime": 1784613600000,
              "fundingIntervalHours": 1
            }
          ],
          [
            "BybitPerp",
            {
              "fundingRate": "0.00008284",
              "nextFundingTime": 1784620800000,
              "fundingIntervalHours": 8
            }
          ]
        ]
      ],
      [
        "BTC",
        [
          [
            "BinPerp",
            {
              "fundingRate": "0.00008538",
              "nextFundingTime": 1784620800000,
              "fundingIntervalHours": 8
            }
          ],
          [
            "HlPerp",
            {
              "fundingRate": "0.0000075892",
              "nextFundingTime": 1784613600000,
              "fundingIntervalHours": 1
            }
          ],
          [
            "BybitPerp",
            {
              "fundingRate": "0.00006005",
              "nextFundingTime": 1784620800000,
              "fundingIntervalHours": 8
            }
          ]
        ]
      ],
      [
        "DOGE",
        [
          [
            "BinPerp",
            {
              "fundingRate": "0.0001",
              "nextFundingTime": 1784620800000,
              "fundingIntervalHours": 8
            }
          ],
          [
            "HlPerp",
            {
              "fundingRate": "0.0000125",
              "nextFundingTime": 1784613600000,
              "fundingIntervalHours": 1
            }
          ],
          [
            "BybitPerp",
            {
              "fundingRate": "0.00002837",
              "nextFundingTime": 1784620800000,
              "fundingIntervalHours": 8
            }
          ]
        ]
      ],
      [
        "ETH",
        [
          [
            "BinPerp",
            {
              "fundingRate": "0.00005477",
              "nextFundingTime": 1784620800000,
              "fundingIntervalHours": 8
            }
          ],
          [
            "HlPerp",
            {
              "fundingRate": "0.0000125",
              "nextFundingTime": 1784613600000,
              "fundingIntervalHours": 1
            }
          ],
          [
            "BybitPerp",
            {
              "fundingRate": "0.0001",
              "nextFundingTime": 1784620800000,
              "fundingIntervalHours": 8
            }
          ]
        ]
      ],
      [
        "HYPE",
        [
          [
            "BinPerp",
            null
          ],
          [
            "HlPerp",
            {
              "fundingRate": "0.0000125",
              "nextFundingTime": 1784613600000,
              "fundingIntervalHours": 1
            }
          ],
          [
            "BybitPerp",
            null
          ]
        ]
      ],
      [
        "LINK",
        [
          [
            "BinPerp",
            {
              "fundingRate": "0.0001",
              "nextFundingTime": 1784620800000,
              "fundingIntervalHours": 8
            }
          ],
          [
            "HlPerp",
            {
              "fundingRate": "0.0000125",
              "nextFundingTime": 1784613600000,
              "fundingIntervalHours": 1
            }
          ],
          [
            "BybitPerp",
            {
              "fundingRate": "0.0001",
              "nextFundingTime": 1784620800000,
              "fundingIntervalHours": 8
            }
          ]
        ]
      ],
      [
        "LTC",
        [
          [
            "BinPerp",
            {
              "fundingRate": "0.0001",
              "nextFundingTime": 1784620800000,
              "fundingIntervalHours": 8
            }
          ],
          [
            "HlPerp",
            {
              "fundingRate": "0.0000125",
              "nextFundingTime": 1784613600000,
              "fundingIntervalHours": 1
            }
          ],
          [
            "BybitPerp",
            {
              "fundingRate": "-0.00002376",
              "nextFundingTime": 1784620800000,
              "fundingIntervalHours": 8
            }
          ]
        ]
      ],
      [
        "SOL",
        [
          [
            "BinPerp",
            {
              "fundingRate": "0.00008485",
              "nextFundingTime": 1784620800000,
              "fundingIntervalHours": 8
            }
          ],
          [
            "HlPerp",
            {
              "fundingRate": "0.0000125",
              "nextFundingTime": 1784613600000,
              "fundingIntervalHours": 1
            }
          ],
          [
            "BybitPerp",
            {
              "fundingRate": "0.0001",
              "nextFundingTime": 1784620800000,
              "fundingIntervalHours": 8
            }
          ]
        ]
      ],
      [
        "SUI",
        [
          [
            "BinPerp",
            {
              "fundingRate": "0.00004105",
              "nextFundingTime": 1784620800000,
              "fundingIntervalHours": 8
            }
          ],
          [
            "HlPerp",
            {
              "fundingRate": "0.0000125",
              "nextFundingTime": 1784613600000,
              "fundingIntervalHours": 1
            }
          ],
          [
            "BybitPerp",
            {
              "fundingRate": "0.0001",
              "nextFundingTime": 1784620800000,
              "fundingIntervalHours": 8
            }
          ]
        ]
      ],
      [
        "XRP",
        [
          [
            "BinPerp",
            {
              "fundingRate": "0.0000475",
              "nextFundingTime": 1784620800000,
              "fundingIntervalHours": 8
            }
          ],
          [
            "HlPerp",
            {
              "fundingRate": "-0.0000175325",
              "nextFundingTime": 1784613600000,
              "fundingIntervalHours": 1
            }
          ],
          [
            "BybitPerp",
            {
              "fundingRate": "0.00006483",
              "nextFundingTime": 1784620800000,
              "fundingIntervalHours": 8
            }
          ]
        ]
      ]
    ],
    "xyzMetaAndAssetCtxs": [
      {
        "universe": [
          {
            "szDecimals": 3,
            "name": "xyz:CL",
            "maxLeverage": 20,
            "marginTableId": 20,
            "growthMode": "enabled",
            "lastGrowthModeChangeTime": "2026-01-06T14:22:02.431616165"
          }
        ],
        "collateralToken": 0
      },
      [
        {
          "funding": "0.00000625",
          "openInterest": "1928484.517999999",
          "prevDayPx": "83.916",
          "dayNtlVlm": "282819449.0704299808",
          "premium": "0.000060931",
          "oraclePx": "82.06",
          "markPx": "82.059",
          "midPx": "82.062",
          "impactPxs": [
            "82.059",
            "82.071"
          ],
          "dayBaseVlm": "3453222.5290000006"
        }
      ]
    ]
  },
  "binance": null,
  "bybit": null,
  "hlCrossCheck": {
    "endpoint": "metaAndAssetCtxs",
    "checked": 11,
    "confirmed": 9,
    "divergences": [
      {
        "coin": "BTC",
        "predictedFundings": "0.0000075892",
        "metaAndAssetCtxs": "0.0000075557"
      },
      {
        "coin": "XRP",
        "predictedFundings": "-0.0000175325",
        "metaAndAssetCtxs": "-0.000017458"
      }
    ],
    "floorSuspects": []
  }
}
